jupyterlab_templates/__init__.py
jupyterlab_templates/_version.py
jupyterlab_templates/extension.py
jupyterlab_templates/extension/install.json
jupyterlab_templates/extension/jupyterlab_templates.json
jupyterlab_templates/extension/notebook_templates/jupyterlab_templates/Sample.ipynb
jupyterlab_templates/labextension/package.json
jupyterlab_templates/labextension/static/509.f3d6362786ae21387b49.js
jupyterlab_templates/labextension/static/remoteEntry.3a60a732201d753f190a.js
jupyterlab_templates/labextension/static/style.js
jupyterlab_templates/labextension/static/third-party-licenses.json
jupyterlab_templates/templates/jupyterlab_templates/Sample.ipynb
jupyterlab_templates/tests/__init__.py
jupyterlab_templates/tests/test_all.py
jupyterlab_templates/tests/test_extension.py
jupyterlab_templates/tests/test_init.py
jupyterlab_templates-0.5.3.data/data/share/jupyter/notebook/jupyterlab_templates/Sample.ipynb
jupyterlab_templates-0.5.3.data/data/etc/jupyter/jupyter_server_config.d/jupyterlab_templates.json
jupyterlab_templates-0.5.3.data/data/share/jupyter/labextensions/jupyterlab_templates/package.json
jupyterlab_templates-0.5.3.data/data/share/jupyter/labextensions/jupyterlab_templates/static/509.f3d6362786ae21387b49.js
jupyterlab_templates-0.5.3.data/data/share/jupyter/labextensions/jupyterlab_templates/static/remoteEntry.3a60a732201d753f190a.js
jupyterlab_templates-0.5.3.data/data/share/jupyter/labextensions/jupyterlab_templates/static/style.js
jupyterlab_templates-0.5.3.data/data/share/jupyter/labextensions/jupyterlab_templates/static/third-party-licenses.json
jupyterlab_templates-0.5.3.data/data/share/jupyter/labextensions/jupyterlab_templates/install.json
jupyterlab_templates-0.5.3.dist-info/METADATA
jupyterlab_templates-0.5.3.dist-info/WHEEL
jupyterlab_templates-0.5.3.dist-info/licenses/AUTHORS
jupyterlab_templates-0.5.3.dist-info/licenses/LICENSE
jupyterlab_templates-0.5.3.dist-info/licenses/NOTICE
jupyterlab_templates-0.5.3.dist-info/RECORD
