Metadata-Version: 2.4
Name: jupyterlab_templates
Version: 0.5.3
Summary: notebook templates for jupyterlab
Project-URL: Repository, https://github.com/finos/jupyterlab_templates
Project-URL: Homepage, https://github.com/finos/jupyterlab_templates
Author: the jupyterlab_templates authors
License:                                  Apache License
License-File: AUTHORS
License-File: LICENSE
License-File: NOTICE
Keywords: FINOS,Jupyter,JupyterLab,JupyterLab Extension,Templates
Classifier: Development Status :: 4 - Beta
Classifier: Framework :: Jupyter
Classifier: Framework :: Jupyter :: JupyterLab
Classifier: License :: OSI Approved :: Apache Software License
Classifier: Programming Language :: Python
Classifier: Programming Language :: Python :: 3
Classifier: Programming Language :: Python :: 3.7
Classifier: Programming Language :: Python :: 3.8
Classifier: Programming Language :: Python :: 3.9
Classifier: Programming Language :: Python :: 3.10
Classifier: Programming Language :: Python :: 3.11
Classifier: Programming Language :: Python :: 3.12
Requires-Python: >=3.7
Requires-Dist: jupyterlab<5,>=4
Provides-Extra: develop
Requires-Dist: check-manifest; extra == 'develop'
Requires-Dist: pytest; extra == 'develop'
Requires-Dist: pytest-cov; extra == 'develop'
Requires-Dist: ruff<0.13,>=0.5.0; extra == 'develop'
Requires-Dist: twine<6.2,>=5; extra == 'develop'
Provides-Extra: test
Requires-Dist: pytest; extra == 'test'
Requires-Dist: pytest-cov; extra == 'test'
